Lab 2/roomtemp.v
module room_temp (temp, ac, fan, heater, all_off, clk, init, q);

    input [5:0] temp; //6-bit temp input
    input clk, init;

    output reg ac, fan, heater, all_off;
    reg [3:0] d;
    output wire [3:0] q;
    output reg [2:0] temp_range;


    dff_4 dff (.clk(clk), .d(d), .q(q), .rst(init));

    //ranges defined according to the definitions given in the problem statement
    always @ (*) begin
        if (temp < 15) begin
            temp_range = 3'b000;
        end
        else if (temp >= 15 & temp <= 18) begin
            temp_range = 3'b001;
        end
        else if (temp > 18 & temp < 22) begin
            temp_range = 3'b010;
        end
        else if (temp == 22) begin
            temp_range = 3'b011;
        end
        else if (temp == 23) begin
            temp_range = 3'b100;
        end
        else if (temp > 23 & temp <= 27) begin
            temp_range = 3'b101;
        end
        else if (temp > 27) begin
            temp_range = 3'b110;
        end
        
        ac = q[3];
        fan = q[2];
        heater = q[1];
        all_off = q[0];
    end

    always @ (temp) begin

        case (q)
            4'b0001: //all off state
            begin
                case (temp_range)
                3'b000: d = 4'b0010; //temp < 15, heater on
                3'b001: d = 4'b0001; //temp >= 15 & temp <= 18, all off
                3'b010: d = 4'b0001; //temp > 18 & temp < 22, all off
                3'b011: d = 4'b0001; //temp == 22, all off
                3'b100: d = 4'b0001; //temp == 23, all off
                3'b101: d = 4'b0100; //temp > 23 & temp <= 27, fan on
                3'b110: d = 4'b1000; //temp > 27, ac on
                endcase
            end
            
            4'b0010: //heater is on
            begin
                case (temp_range)
                3'b000: d = 4'b0010; //temp < 15, heater on
                3'b001: d = 4'b0010; //temp >= 15 & temp <= 18, heater on
                3'b010: d = 4'b0001; //temp > 18 & temp < 22, all off
                3'b011: d = 4'b0001; //temp == 22, all off
                3'b100: d = 4'b0001; //temp == 23, all off
                3'b101: d = 4'b0100; //temp > 23 & temp <= 27, fan on
                3'b110: d = 4'b1000; //temp > 27, ac on
                endcase
            end
            
            4'b0100: //fan is on
            begin
                case (temp_range)
                3'b000: d = 4'b0010; //temp < 15, heater on
                3'b001: d = 4'b0001; //temp >= 15 & temp <= 18, all off
                3'b010: d = 4'b0001; //temp > 18 & temp < 22, all off
                3'b011: d = 4'b0100; //temp == 22, fan remains on
                3'b100: d = 4'b0100; //temp == 23, fan remains on
                3'b101: d = 4'b0100; //temp > 23 & temp <= 27, fan remains on
                3'b110: d = 4'b1000; //temp > 27, ac on
                endcase
            end
            
            4'b1000:  //ac is on
            begin
                case (temp_range)
                3'b000: d = 4'b0010; //temp < 15, heater on
                3'b001: d = 4'b0001; //temp >= 15 & temp <= 18, all off
                3'b010: d = 4'b0001; //temp > 18 & temp < 22, all off
                3'b011: d = 4'b0100; //temp == 22, ac off, fan on
                3'b100: d = 4'b1000; //temp == 23, ac remains on
                3'b101: d = 4'b1000; //temp > 23 & temp <= 27, ac remains on
                3'b110: d = 4'b1000; //temp > 27, ac remains on
                endcase 
            end
        
        endcase
    end
endmodule

module dff_4 (clk, d, q, rst);
    input clk, rst;
    input [3:0] d;
    output reg [3:0] q;

    always @ (posedge clk or negedge rst)
        if (!rst)
            q <= 4'b0000;
        else
            q <= d;
endmodule

Lab 2/roomtemp_tb.v
`include "roomtemp.v"

module tb;

reg [5:0] in;
reg rst;
reg clock;
wire ac, fan, heater, all_off;
wire [3:0] state;

room_temp temp_control (.temp(in), .clk(clock), .ac(ac), .fan(fan), .heater(heater), .all_off(all_off), .init(rst), .q(state));

always #5 clock = ~clock;

initial begin
    $dumpfile("roomtemp.vcd");
    $dumpvars(0, tb);
    $monitor($time, "Temperature = %2d, AC = %b, Heater = %b, Fan = %b, State = %4b", in, ac, heater, fan, state);

    clock = 1'b0;
    rst = 1'b1;
     
    #2 rst = 1'b0;
    temp_control.d = 4'b0001;
    #4 rst = 1'b1;

    #10 in = 6'd17;
    #10 in = 6'd10;
    #10 in = 6'd17;
    #10 in = 6'd23;
    #10 in = 6'd25;
    #10 in = 6'd23;
    #10 in = 6'd22;
    #10 in = 6'd21;
    #10 in = 6'd25;
    #10 in = 6'd28;
    #10 in = 6'd23;
    #10 in = 6'd22;
    #10 in = 6'd13;
    #10 in = 6'd30;
    #10 in = 6'd20;
    
    #10 $finish;
end
endmodule

Lab 2/roomtemp.vcd
$date
	Tue Mar 29 16:32:27 2022
$end
$version
	Icarus Verilog
$end
$timescale
	1s
$end
$scope module tb $end
$var wire 4 ! state [3:0] $end
$var wire 1 " heater $end
$var wire 1 # fan $end
$var wire 1 $ all_off $end
$var wire 1 % ac $end
$var reg 1 & clock $end
$var reg 6 ' in [5:0] $end
$var reg 1 ( rst $end
$scope module temp_control $end
$var wire 1 & clk $end
$var wire 1 ( init $end
$var wire 6 ) temp [5:0] $end
$var wire 4 * q [3:0] $end
$var reg 1 % ac $end
$var reg 1 $ all_off $end
$var reg 4 + d [3:0] $end
$var reg 1 # fan $end
$var reg 1 " heater $end
$var reg 3 , temp_range [2:0] $end
$scope module dff $end
$var wire 1 & clk $end
$var wire 4 - d [3:0] $end
$var wire 1 ( rst $end
$var reg 4 . q [3:0] $end
$upscope $end
$upscope $end
$upscope $end
$enddefinitions $end
#0
$dumpvars
bx .
bx -
bx ,
bx +
bx *
bx )
1(
bx '
0&
x%
x$
x#
x"
bx !
$end
#2
0$
0"
0#
0%
b0 !
b0 *
b0 .
b1 +
b1 -
0(
#5
1&
#6
1(
#10
0&
#15
1$
b1 !
b1 *
b1 .
1&
#16
b1 ,
b10001 '
b10001 )
#20
0&
#25
1&
#26
b10 +
b10 -
b0 ,
b1010 '
b1010 )
#30
0&
#35
0$
1"
b10 !
b10 *
b10 .
1&
#36
b1 ,
b10001 '
b10001 )
#40
0&
#45
1&
#46
b1 +
b1 -
b100 ,
b10111 '
b10111 )
#50
0&
#55
1$
0"
b1 !
b1 *
b1 .
1&
#56
b100 +
b100 -
b101 ,
b11001 '
b11001 )
#60
0&
#65
0$
1#
b100 !
b100 *
b100 .
1&
#66
b100 ,
b10111 '
b10111 )
#70
0&
#75
1&
#76
b11 ,
b10110 '
b10110 )
#80
0&
#85
1&
#86
b1 +
b1 -
b10 ,
b10101 '
b10101 )
#90
0&
#95
1$
0#
b1 !
b1 *
b1 .
1&
#96
b100 +
b100 -
b101 ,
b11001 '
b11001 )
#100
0&
#105
0$
1#
b100 !
b100 *
b100 .
1&
#106
b1000 +
b1000 -
b110 ,
b11100 '
b11100 )
#110
0&
#115
0#
1%
b1000 !
b1000 *
b1000 .
1&
#116
b100 ,
b10111 '
b10111 )
#120
0&
#125
1&
#126
b100 +
b100 -
b11 ,
b10110 '
b10110 )
#130
0&
#135
1#
0%
b100 !
b100 *
b100 .
1&
#136
b10 +
b10 -
b0 ,
b1101 '
b1101 )
#140
0&
#145
1"
0#
b10 !
b10 *
b10 .
1&
#146
b1000 +
b1000 -
b110 ,
b11110 '
b11110 )
#150
0&
#155
0"
1%
b1000 !
b1000 *
b1000 .
1&
#156
b1 +
b1 -
b10 ,
b10100 '
b10100 )
#160
0&
#165
1$
0%
b1 !
b1 *
b1 .
1&
